hwpfc/__init__.py
hwpfc/__main__.py
hwpfc/run.py
hwpfc-0.0.5.dist-info/METADATA
hwpfc-0.0.5.dist-info/WHEEL
hwpfc-0.0.5.dist-info/entry_points.txt
hwpfc-0.0.5.dist-info/top_level.txt
hwpfc-0.0.5.dist-info/RECORD
