Metadata-Version: 2.1
Name: hwpfc
Version: 0.0.5
Summary: Hello word from pfc
Home-page: UNKNOWN
Author: UNKNOWN
Author-email: UNKNOWN
License: UNKNOWN
Platform: UNKNOWN
Requires-Dist: feedparser
Requires-Dist: html2text
